googledriveapi/__init__.py
googledriveapi/storage.py
googledriveapi/tests.py
django_googledrive_api-0.2.5.dist-info/LICENSE.txt
django_googledrive_api-0.2.5.dist-info/METADATA
django_googledrive_api-0.2.5.dist-info/WHEEL
django_googledrive_api-0.2.5.dist-info/dependency_links.txt
django_googledrive_api-0.2.5.dist-info/top_level.txt
django_googledrive_api-0.2.5.dist-info/RECORD
